ddv/__init__.py
ddv/settings/__init__.py
ddv_settings-0.1.1.dist-info/WHEEL
ddv_settings-0.1.1.dist-info/METADATA
ddv_settings-0.1.1.dist-info/RECORD
