Metadata-Version: 2.1
Name: ddv-settings
Version: 0.1.1
Summary: Module for easily reading and exporting settings from files
Home-page: https://gitlab.com/davidevi/ddv-settings
License: Unlicense
Keywords: ddv,settings,ini,config,read,export
Author: Davide Vitelaru
Author-email: davide@vitelaru.com
Requires-Python: >=3.9,<4.0
Classifier: License :: Other/Proprietary License
Classifier: Programming Language :: Python :: 3
Classifier: Programming Language :: Python :: 3.9
Requires-Dist: configparser (>=5.2.0,<6.0.0)
Project-URL: Repository, https://gitlab.com/davidevi/ddv-settings
